README.md
setup.cfg
setup.py
ftfbroker/__init__.py
ftfbroker/environment.py
ftfbroker/exception.py
ftfbroker/protoutils.py
ftfbroker/py.typed
ftfbroker/topic.py
ftfbroker.egg-info/PKG-INFO
ftfbroker.egg-info/SOURCES.txt
ftfbroker.egg-info/dependency_links.txt
ftfbroker.egg-info/requires.txt
ftfbroker.egg-info/top_level.txt
ftfbroker/consumer/__init__.py
ftfbroker/consumer/general_consumer.py
ftfbroker/producer/__init__.py
ftfbroker/producer/automate_stock.py
ftfbroker/producer/general_producer.py
ftfbroker/producer/rocketchat_mensa.py
ftfbroker/protobuf/__init__.py
ftfbroker/protobuf/common/__init__.py
ftfbroker/protobuf/common/metaData_pb2.py
ftfbroker/protobuf/ftf/__init__.py
ftfbroker/protobuf/ftf/automate_stock_pb2.py
ftfbroker/protobuf/ftf/rocketchat_mensa_pb2.py