Metadata-Version: 2.1
Name: ftfbroker
Version: 0.0.3
Summary: Protobuf definitions and python clients for ftf services
Home-page: https://github.com/fachschaft/ftfbroker
Author: Stefan Möhrle
Author-email: moehrles@tf.uni-freiburg.de
License: MIT
Keywords: kafka,protobuf,python
Platform: UNKNOWN
Classifier: Development Status :: 4 - Beta
Classifier: Intended Audience :: Developers
Classifier: License :: OSI Approved :: MIT License
Requires-Python: >=3.7
